jitsreport/.pyarmor.ikey
jitsreport/__init__.py
jitsreport/core.py
jitsreport/pyarmor_runtime_000000/__init__.py
jitsreport/pyarmor_runtime_000000/linux_x86_64/__init__.py
jitsreport/pyarmor_runtime_000000/linux_x86_64/pyarmor_runtime.so
jitsreport/pyarmor_runtime_000000/windows_x86_64/__init__.py
jitsreport/pyarmor_runtime_000000/windows_x86_64/pyarmor_runtime.pyd
jitsreport-0.2.1.4.dist-info/METADATA
jitsreport-0.2.1.4.dist-info/WHEEL
jitsreport-0.2.1.4.dist-info/top_level.txt
jitsreport-0.2.1.4.dist-info/RECORD
