Metadata-Version: 2.4
Name: jitsreport
Version: 0.2.1.4
Summary: A package for generating automated data profiling reports.
Author: Surajit Das
Author-email: mr.surajitdas@gmail.com
Classifier: Programming Language :: Python :: 3
Requires-Python: >=3.6
Requires-Dist: pandas
Requires-Dist: numpy
Requires-Dist: plotly
Requires-Dist: pdfkit
Requires-Dist: openpyxl
Requires-Dist: scipy
Requires-Dist: matplotlib
Requires-Dist: statsmodels
Requires-Dist: jinja2
Dynamic: author
Dynamic: author-email
Dynamic: classifier
Dynamic: description
Dynamic: description-content-type
Dynamic: requires-dist
Dynamic: requires-python
Dynamic: summary
